CHANGELOG.md
CONTRIBUTING.md
LICENSE.md
README.md
requirements.txt
setup.cfg
setup.py
backtesting/__init__.py
backtesting/_plotting.py
backtesting/_util.py
backtesting/_version.py
backtesting/autoscale_cb.js
backtesting/backtesting.py
backtesting/lib.py
backtesting/test/__init__.py
backtesting/test/__main__.py
backtesting/test/_test.py
foxbt.egg-info/PKG-INFO
foxbt.egg-info/SOURCES.txt
foxbt.egg-info/dependency_links.txt
foxbt.egg-info/requires.txt
foxbt.egg-info/top_level.txt