Metadata-Version: 2.1
Name: foxbt
Version: 0.2.9
Summary: Backtest trading strategies in Python
Home-page: https://kernc.github.io/backtesting.py/
Author: Zach Lûster
License: AGPL-3.0
Project-URL: Documentation, https://kernc.github.io/backtesting.py/doc/backtesting/
Project-URL: Source, https://github.com/thefoxquant/foxbt/
Project-URL: Tracker, https://github.com/thefoxquant/foxbt
Keywords: algo,algorithmic,ashi,backtest,backtesting,bitcoin,bokeh,bonds,candle,candlestick,cboe,chart,cme,commodities,crash,crypto,currency,doji,drawdown,equity,etf,ethereum,exchange,finance,financial,forecast,forex,fund,futures,fx,fxpro,gold,heiken,historical,indicator,invest,investing,investment,macd,market,mechanical,money,oanda,ohlc,ohlcv,order,price,profit,quant,quantitative,rsi,silver,stocks,strategy,ticker,trader,trading,tradingview,usd
Platform: UNKNOWN
Classifier: Intended Audience :: Financial and Insurance Industry
Classifier: Intended Audience :: Science/Research
Classifier: License :: OSI Approved :: GNU Affero General Public License v3 or later (AGPLv3+)
Classifier: Operating System :: OS Independent
Classifier: Programming Language :: Python :: 3 :: Only
Classifier: Topic :: Office/Business :: Financial :: Investment
Classifier: Topic :: Scientific/Engineering :: Visualization
Requires-Python: >=3.6
Provides-Extra: doc
Provides-Extra: test
Provides-Extra: dev
